{"developers_arbitrum-full-node.md":"08663847","community_modular-meetup-toolkit.md":"f570be94","community_coc.md":"59b512dc","developers_arbitrum-bridge.md":"1acaa46d","community_calendar.md":"c5ef2ced","readme.md":"edc85355","developers_arbitrum-smart-contract.md":"fad43bad","community_itn-tos.md":"e236ec8e","developers_arbitrum-dapp-deploy.md":"427a3997","community_modular-meetup-intro.md":"4c692bac","developers_arbitrum-integration.md":"5ac9e003","community_modular-meetup-guide.md":"1e781899","nodes_celestia-node-custom-networks.md":"567aa086","nodes_decide-node.md":"5f0968f3","nodes_overview.md":"90fddb0c","nodes_celestia-node-metrics.md":"53583892","nodes_quick-start.md":"8736a835","nodes_hardfork-process.md":"11f2d6e2","nodes_config-toml.md":"b345cf03","learn_how-celestia-works_monolithic-vs-modular.md":"b65558ff","developers_ethereum-fallback.md":"de2ef684","developers_blobstream-contracts.md":"1da9b86e","learn_how-celestia-works_transaction-lifecycle.md":"74a81342","developers_bubs-testnet.md":"c44ed57a","developers_blobstream-offchain.md":"38008636","developers_arbitrum-deploy.md":"b9b11e65","developers_optimism-devnet.md":"bdccab75","community_speaker-list.md":"3483a48c","nodes_celestia-app-metrics.md":"bb95313b","nodes_celestia-node.md":"969e2df9","developers_blobstream-x-deploy.md":"fced7c0a","nodes_light-node.md":"83e32aaf","nodes_environment.md":"ebebf73d","community_foundation-delegation-program.md":"48c30b9c","nodes_systemd.md":"a7063d90","nodes_celestia-app-slashing.md":"cba47e29","nodes_celestia-node-troubleshooting.md":"1126fabb","nodes_celestia-app-upgrade-monitor.md":"b363c541","nodes_participate.md":"69d27e41","developers_deploy-on-bubs.md":"04521ed3","developers_full-stack-modular-development-guide.md":"a6c793df","nodes_ibc-relayer.md":"9bfd31d2","nodes_mainnet.md":"dc13f222","developers_blobstream.md":"407ca283","developers_build-whatever.md":"dfe5ba39","nodes_instantiate-testnet.md":"b19e267b","learn_paying-for-blobspace.md":"804e7e0a","nodes_celestia-app-wallet.md":"f895505c","developers_rollkit.md":"adfe8560","nodes_full-storage-node.md":"825367f9","nodes_mocha-testnet.md":"c69b01b6","developers_transaction-resubmission.md":"90de2399","index.md":"51ee5fd9","developers_optimism.md":"d43bdda0","nodes_celestia-app-multisig.md":"593547b0","developers_intro-to-op-stack.md":"cb0561cb","learn_how-celestia-works_data-availability-faq.md":"6a5fd8d4","developers_requesting-data-commitment-ranges.md":"59e6357e","developers_integrate-celestia.md":"50c60b52","developers_gm-portal-bubs.md":"5ad58a96","developers_submit-data.md":"effa42d7","learn_how-to-stake-tia.md":"199f0abc","nodes_celestia-app-commands.md":"5fa56b78","community_overview.md":"c0640a79","nodes_arabica-devnet.md":"bb9c82b3","developers_wallets.md":"a108e73d","developers_blobstream-proof-queries.md":"0dc64226","learn_how-celestia-works_data-availability-layer.md":"29316b09","learn_how-celestia-works_overview.md":"8667aade","nodes_celestia-app-vesting.md":"b7a3154c","developers_node-api.md":"dcffb3a0","learn_staking-governance-supply.md":"cc584192","developers_blobstream-rollups.md":"bfce0000","learn_tia.md":"6e27e423","nodes_docker-images.md":"33167a5f","nodes_validator-node.md":"8df7380a","learn_retrievability.md":"90e3bcc3","nodes_celestia-app.md":"9eb0c0a5","learn_staking.md":"6df9fd47","nodes_bridge-node.md":"c300f1f8","developers_prompt-scavenger.md":"b3fe160b","nodes_full-consensus-node.md":"0124ec2d","developers_node-tutorial.md":"0b94f41b","developers_celestia-node-key.md":"e8461edd"}
