{"community_modular-meetup-toolkit.md":"76dafd52","community_coc.md":"152c60a4","developers_arbitrum-integration.md":"f9e17a6f","community_foundation-delegation-program.md":"e474a5dc","developers_blobstream-contracts.md":"c91f3561","community_speaker-list.md":"908bb589","developers_bubs-testnet.md":"e7dfaebb","learn_retrievability.md":"6aa17c7f","readme.md":"ff2fe119","learn_how-celestia-works_monolithic-vs-modular.md":"6ee57fcd","learn_how-celestia-works_overview.md":"895651ce","learn_how-celestia-works_transaction-lifecycle.md":"5e062d70","learn_how-to-stake-tia.md":"8a8e0da1","learn_paying-for-blobspace.md":"3c3b5c65","developers_rust-client-tutorial.md":"cc1b9af2","developers_blobstream-offchain.md":"406dcfff","developers_transaction-resubmission.md":"fc462af9","developers_node-api.md":"e91b3363","developers_multiaccounts.md":"8d2aaf24","developers_integrate-celestia.md":"0108f4e5","developers_blobstream-x-requesting-data-commitment-ranges.md":"48a8f19d","developers_arbitrum-bridge.md":"c337b894","nodes_celestia-node-metrics.md":"baa2283a","learn_how-celestia-works_data-availability-faq.md":"186b6eb0","developers_optimism-devnet.md":"45c16f20","developers_optimism.md":"6d3d0dde","developers_sp1-blobstream-deploy.md":"8abc74dd","nodes_celestia-app.md":"bff16575","nodes_celestia-node-custom-networks.md":"ad92b055","nodes_celestia-app-wallet.md":"caa02cc2","developers_blobstream-rollups.md":"771e724b","developers_arbitrum-full-node.md":"2a07486c","learn_how-celestia-works_data-availability-layer.md":"a80b5da2","developers_blobstream.md":"a5b75643","developers_node-tutorial.md":"86784644","developers_intro-to-op-stack.md":"c746f10a","nodes_celestia-node.md":"7e937726","developers_submit-data.md":"54e5f21f","nodes_celestia-node-troubleshooting.md":"bfb45df0","nodes_docker-images.md":"6920b7c2","developers_blobstream-proof-queries.md":"d2b7e3cc","developers_blobstream-x-deploy.md":"e2f17303","developers_feegrant-for-blobs.md":"854d1c3b","developers_wallets.md":"25a831ec","nodes_decide-node.md":"d29d875e","nodes_environment.md":"f168f624","nodes_config-toml.md":"90793f0b","nodes_celestia-node-trusted-hash.md":"ca2bfc63","learn_staking-governance-supply.md":"25a23727","nodes_mocha-testnet.md":"60da967c","nodes_full-storage-node.md":"acca0ae8","nodes_network-upgrade-process.md":"2942e64a","nodes_overview.md":"257b2b2b","nodes_participate.md":"dc4d95a4","nodes_quick-start.md":"b3473afd","nodes_arabica-devnet.md":"ec31de0c","nodes_validator-node.md":"117d7403","learn_staking.md":"b38e8f65","nodes_consensus-node.md":"688caf62","nodes_light-node.md":"158ef685","developers_celestia-node-key.md":"f919cf75","nodes_instantiate-testnet.md":"a44213c6","developers_arbitrum-deploy.md":"0684a2bc","nodes_celestia-app-multisig.md":"21c9957b","nodes_bridge-node.md":"21c4c48c","nodes_systemd.md":"bafed34e","nodes_ibc-relayer.md":"4c81e4bb","community_modular-meetup-guide.md":"8abcd2e7","developers_prompt-scavenger.md":"dd155768","nodes_celestia-app-vesting.md":"e9312cb1","community_modular-meetup-intro.md":"2f254b32","developers_build-whatever.md":"1316b8bc","nodes_mainnet.md":"7e7498d5","developers_golang-client-tutorial.md":"6fb4740e","nodes_celestia-app-upgrade-monitor.md":"7b757079","nodes_celestia-app-slashing.md":"548aee87","developers_blobstreamx.md":"ac7e18aa","index.md":"662dc62b","developers_ethereum-fallback.md":"eb85843c","learn_tia.md":"a12dae5b","nodes_celestia-app-metrics.md":"c7446423","nodes_celestia-app-commands.md":"ca1cafbb"}
