{"developers_arbitrum-integration.md":"29e35991","developers_node-api.md":"a5114dad","community_foundation-delegation-program.md":"81eeee80","nodes_celestia-app.md":"96cf5fc9","developers_arbitrum-deploy.md":"828809c8","nodes_config-toml.md":"e378452d","nodes_celestia-node-custom-networks.md":"080a3ba8","developers_blobstream-x-deploy.md":"8bfb326c","nodes_celestia-node-metrics.md":"66638f7a","developers_bubs-testnet.md":"09d28edc","developers_blobstream.md":"ff980190","nodes_celestia-node-troubleshooting.md":"527ea496","nodes_mocha-testnet.md":"ed770ab1","nodes_light-node.md":"6b215a00","learn_how-to-stake-tia.md":"27353951","learn_paying-for-blobspace.md":"7a788a2e","developers_celestia-node-key.md":"6a0e3f5e","developers_requesting-data-commitment-ranges.md":"194aedc7","nodes_docker-images.md":"6fbf6333","community_speaker-list.md":"0d356c21","nodes_bridge-node.md":"7620fe2b","nodes_celestia-app-vesting.md":"5dc97e54","nodes_ibc-relayer.md":"d03225a5","learn_tia.md":"7292dd22","learn_how-celestia-works_transaction-lifecycle.md":"01a4a611","nodes_celestia-app-commands.md":"bc01c525","nodes_consensus-node.md":"12e5155d","learn_staking.md":"8fa861fa","developers_rollup-overview.md":"7a68510a","nodes_celestia-app-upgrade-monitor.md":"9a23ba3f","learn_retrievability.md":"a3c1cec8","learn_staking-governance-supply.md":"474ddcf2","developers_integrate-celestia.md":"c66cc4d9","developers_optimism.md":"1cd4a890","learn_how-celestia-works_data-availability-faq.md":"5acbaf94","community_modular-meetup-guide.md":"989e0164","community_overview.md":"424b5072","community_calendar.md":"fc11b271","developers_blobstream-proof-queries.md":"53871c51","developers_prompt-scavenger.md":"e507546c","nodes_arabica-devnet.md":"45025cd2","developers_arbitrum-smart-contract.md":"1c654019","developers_arbitrum-dapp-deploy.md":"6f7cd4fe","readme.md":"93669917","nodes_overview.md":"1d586236","learn_how-celestia-works_overview.md":"2e087982","nodes_participate.md":"b78f8884","learn_how-celestia-works_monolithic-vs-modular.md":"ea4e28be","developers_arbitrum-mocha.md":"0aa20605","nodes_quick-start.md":"b99e305f","developers_transaction-resubmission.md":"57c14687","developers_build-modular.md":"18c7d06b","nodes_full-storage-node.md":"239509fc","nodes_hardfork-process.md":"abcc9b5d","developers_submit-data.md":"f2d52921","developers_rollkit.md":"aef7efdb","nodes_instantiate-testnet.md":"98d6888d","nodes_decide-node.md":"671eb588","nodes_celestia-app-wallet.md":"5dfd727a","learn_how-celestia-works_data-availability-layer.md":"800aa9fc","community_itn-tos.md":"aae076ab","nodes_celestia-app-metrics.md":"440a0f39","community_modular-meetup-intro.md":"b7763ba4","nodes_celestia-app-multisig.md":"cf0a91b4","developers_gm-portal-bubs.md":"4240102c","developers_blobstream-offchain.md":"cc9c41d3","developers_blobstream-contracts.md":"798ec8f1","developers_ethereum-fallback.md":"6c5d8a45","nodes_celestia-app-slashing.md":"69181ea9","community_coc.md":"9d17ee0b","developers_nitrogen.md":"38c8861e","developers_node-tutorial.md":"c20d1802","developers_full-stack-modular-development-guide.md":"c61e7755","developers_deploy-on-bubs.md":"6138bb83","nodes_environment.md":"5de34f8b","developers_intro-to-op-stack.md":"307cc275","nodes_systemd.md":"592aaf07","developers_optimism-devnet.md":"db3ef3eb","developers_wallets.md":"8a842396","nodes_mainnet.md":"6d507d69","index.md":"e3b0f360","community_modular-meetup-toolkit.md":"6e50a131","nodes_celestia-node.md":"2194cc29"}
