{"developers_blobstream-x-requesting-data-commitment-ranges.md":"e723a20f","developers_blobstream-contracts.md":"bb82129e","developers_blobstream.md":"718589e0","developers_deploy-on-bubs.md":"88d5643f","community_calendar.md":"d666d16d","community_foundation-delegation-program.md":"c2ff155b","developers_arbitrum-integration.md":"560187ea","developers_ethereum-fallback.md":"76daf8fc","community_speaker-list.md":"bf031997","developers_integrate-celestia.md":"c10af26c","developers_node-tutorial.md":"ad65bdbd","community_modular-meetup-guide.md":"91d3dbb6","developers_golang-client-tutorial.md":"294c0f77","developers_optimism-devnet.md":"2187e56b","developers_build-whatever.md":"c04dfe1c","index.md":"b9c5bf0f","developers_blobstream-rollups.md":"69312229","learn_how-celestia-works_overview.md":"030bc36b","learn_how-celestia-works_data-availability-layer.md":"0aa8d3a8","learn_how-celestia-works_transaction-lifecycle.md":"33cc305a","developers_arbitrum-full-node.md":"4524c52f","community_modular-meetup-intro.md":"b62325b8","developers_blobstream-x-deploy.md":"b6a0be2d","readme.md":"a4b0aea2","developers_blobstream-proof-queries.md":"eb3f210b","community_modular-meetup-toolkit.md":"4de3f3de","community_itn-tos.md":"26a309f2","community_coc.md":"acfe6273","learn_how-celestia-works_data-availability-faq.md":"323ea5f2","developers_node-api.md":"8c85c081","developers_transaction-resubmission.md":"b4116177","developers_gm-portal-bubs.md":"f432f21e","developers_arbitrum-smart-contract.md":"cef83772","learn_how-celestia-works_monolithic-vs-modular.md":"21976b19","community_overview.md":"3fd6c055","developers_arbitrum-bridge.md":"8aba057e","developers_wallets.md":"275f3df3","developers_prompt-scavenger.md":"26f9c464","nodes_celestia-app-wallet.md":"85ab0914","nodes_celestia-app-vesting.md":"b84e1211","learn_tia.md":"94b374bb","nodes_celestia-app-upgrade-monitor.md":"1caa1a43","nodes_config-toml.md":"53418dce","nodes_celestia-node-trusted-hash.md":"df9e1e8c","developers_arbitrum-dapp-deploy.md":"fa5a4fee","nodes_full-storage-node.md":"1d4bd1f5","learn_how-to-stake-tia.md":"835f46bf","developers_arbitrum-deploy.md":"03f7186b","learn_paying-for-blobspace.md":"58f4bfdc","nodes_environment.md":"a04da4d7","learn_retrievability.md":"8bb34e16","learn_staking-governance-supply.md":"1a9a2dfc","nodes_celestia-app-commands.md":"e4641255","nodes_celestia-app-slashing.md":"404b1784","nodes_celestia-app-multisig.md":"2b3408f8","developers_intro-to-op-stack.md":"953a0f5e","nodes_celestia-app-metrics.md":"6f2e04ab","developers_full-stack-modular-development-guide.md":"28da0394","developers_blobstream-offchain.md":"948edd33","nodes_hardfork-process.md":"fa371eb4","nodes_celestia-node-custom-networks.md":"bd313158","nodes_celestia-app.md":"9128d343","nodes_docker-images.md":"d4d07683","nodes_light-node.md":"b55eebc8","nodes_mocha-testnet.md":"477badae","nodes_mainnet.md":"b09e4c24","nodes_participate.md":"be2298ed","nodes_quick-start.md":"d8517b0e","nodes_overview.md":"f2db7c51","nodes_arabica-devnet.md":"cb193349","nodes_celestia-node.md":"2dd89486","nodes_validator-node.md":"3938e252","nodes_systemd.md":"a4c3e0fb","nodes_bridge-node.md":"4aaba6bc","learn_staking.md":"4913a3f5","developers_rust-client-tutorial.md":"fee4806c","nodes_instantiate-testnet.md":"f01a1bec","nodes_decide-node.md":"3b93394e","nodes_celestia-node-metrics.md":"65a32eb5","developers_celestia-node-key.md":"eb176e6a","nodes_ibc-relayer.md":"a260f843","developers_feegrant-for-blobs.md":"4fbc7f11","developers_submit-data.md":"99af16ed","developers_optimism.md":"3f23341a","developers_bubs-testnet.md":"6b7edb4e","nodes_celestia-node-troubleshooting.md":"aeaf3226","nodes_consensus-node.md":"de11d0c3"}
