{"community_calendar.md":"f53d2153","developers_blobstream-contracts.md":"af0b1d17","community_modular-meetup-toolkit.md":"91e69b68","community_modular-meetup-intro.md":"995b7adc","developers_arbitrum-integration.md":"796fe527","developers_arbitrum-full-node.md":"0c4af7a7","community_modular-meetup-guide.md":"de0d70ed","nodes_celestia-app-vesting.md":"a55946ce","nodes_hardfork-process.md":"5007009c","nodes_validator-node.md":"9ba0e389","nodes_environment.md":"d6ad07bf","nodes_participate.md":"f8d17eaa","nodes_quick-start.md":"b41a6a1b","developers_integrate-celestia.md":"358f6583","readme.md":"e3e0bce6","developers_blobstream-offchain.md":"bf72b6d0","nodes_full-storage-node.md":"4761f4f8","nodes_full-consensus-node.md":"de645fd8","community_coc.md":"f6b243f5","index.md":"1563d2c8","learn_how-celestia-works_data-availability-faq.md":"af1edaad","community_overview.md":"d9852d5f","developers_wallets.md":"937c8620","nodes_systemd.md":"85e13d14","developers_arbitrum-dapp-deploy.md":"27566d77","developers_prompt-scavenger.md":"6a1eaed6","developers_arbitrum-bridge.md":"97c664a1","developers_intro-to-op-stack.md":"5acf336c","developers_node-api.md":"7b226896","learn_how-celestia-works_transaction-lifecycle.md":"87251995","nodes_overview.md":"3e3316e4","developers_blobstream-x-requesting-data-commitment-ranges.md":"249be3bf","developers_bubs-testnet.md":"5344bf63","developers_blobstream.md":"99b7a255","developers_arbitrum-deploy.md":"99cc20e7","learn_retrievability.md":"bb01786e","community_foundation-delegation-program.md":"ee1f3b19","developers_build-whatever.md":"cf36e88e","developers_optimism.md":"f80006df","nodes_celestia-node.md":"a1fbc073","developers_blobstream-rollups.md":"3bfa536d","developers_blobstream-x-deploy.md":"8a1baa48","nodes_config-toml.md":"5530ce30","nodes_celestia-app-wallet.md":"ce714a7d","nodes_celestia-app-slashing.md":"d45380f3","community_itn-tos.md":"fcb34914","nodes_celestia-node-custom-networks.md":"83465575","nodes_decide-node.md":"4e8bfd35","nodes_celestia-node-metrics.md":"9fedb1a4","developers_submit-data.md":"2804e854","developers_ethereum-fallback.md":"9c90896e","nodes_celestia-node-troubleshooting.md":"8906e44e","developers_full-stack-modular-development-guide.md":"d77d6ac2","developers_node-tutorial.md":"c1afe499","developers_gm-portal-bubs.md":"a6e4da1d","learn_staking-governance-supply.md":"05a06f8b","developers_arbitrum-smart-contract.md":"ca840f48","nodes_ibc-relayer.md":"2d93ca86","developers_golang-client-tutorial.md":"5377f3b8","nodes_mocha-testnet.md":"1e908973","developers_deploy-on-bubs.md":"e1920b11","nodes_instantiate-testnet.md":"6507f8c4","developers_optimism-devnet.md":"99bf8d6b","learn_paying-for-blobspace.md":"573006a4","learn_how-to-stake-tia.md":"55d7a5f5","nodes_mainnet.md":"10433a64","developers_blobstream-proof-queries.md":"d4933690","nodes_celestia-app-multisig.md":"659f2d1a","learn_how-celestia-works_data-availability-layer.md":"6342b044","learn_staking.md":"32e7976b","nodes_arabica-devnet.md":"d2c88429","learn_tia.md":"96e95579","learn_how-celestia-works_monolithic-vs-modular.md":"288bfb15","developers_transaction-resubmission.md":"c167c290","nodes_celestia-app-commands.md":"583b581c","nodes_bridge-node.md":"37e97282","nodes_celestia-app.md":"21612750","nodes_light-node.md":"b4c8b396","nodes_celestia-app-upgrade-monitor.md":"54569912","developers_rust-client-tutorial.md":"c3fa3a41","learn_how-celestia-works_overview.md":"8f5d22aa","developers_celestia-node-key.md":"286821d9","community_speaker-list.md":"d8e637c7","nodes_docker-images.md":"d6299dea","nodes_celestia-app-metrics.md":"f04dff85"}
