{"community_coc.md":"b286656f","community_foundation-delegation-program.md":"5e38fb6f","community_overview.md":"a474a862","readme.md":"ee255a39","developers_blobstream-x-requesting-data-commitment-ranges.md":"2c30a6e1","developers_blobstream.md":"4753ad66","developers_gm-portal-bubs.md":"a5cb61dd","community_itn-tos.md":"4b4d828f","community_calendar.md":"b4d051e5","community_speaker-list.md":"29de1def","developers_arbitrum-deploy.md":"8ee54f0e","developers_intro-to-op-stack.md":"0a9b0002","developers_feegrant-for-blobs.md":"f68284ba","developers_blobstream-rollups.md":"43816d89","developers_arbitrum-dapp-deploy.md":"f3adaf05","developers_blobstream-contracts.md":"ad69c9fd","community_modular-meetup-intro.md":"81e71862","developers_full-stack-modular-development-guide.md":"53558804","learn_how-celestia-works_monolithic-vs-modular.md":"dcf7de14","learn_how-celestia-works_overview.md":"4a4da1a5","developers_arbitrum-bridge.md":"dfbeaf2d","learn_how-to-stake-tia.md":"8e78cdaf","learn_tia.md":"cb1be470","developers_wallets.md":"aa7ccee0","nodes_ibc-relayer.md":"25e5e4d7","nodes_hardfork-process.md":"3600ad05","nodes_instantiate-testnet.md":"648fb34d","nodes_light-node.md":"85b6e495","nodes_mocha-testnet.md":"4c07ed6b","nodes_overview.md":"841fd781","nodes_celestia-app-wallet.md":"d8086609","learn_staking.md":"9b2d3db2","developers_integrate-celestia.md":"64595e4f","nodes_celestia-node-custom-networks.md":"9f2a4fdd","nodes_decide-node.md":"15209ffa","nodes_participate.md":"54e93c2a","nodes_celestia-app-upgrade-monitor.md":"a687cab7","nodes_celestia-app-slashing.md":"2ebd6f7d","developers_golang-client-tutorial.md":"d8fcb0d3","nodes_config-toml.md":"39796dbc","nodes_systemd.md":"b0980f97","developers_ethereum-fallback.md":"8d96c1a1","nodes_quick-start.md":"b48d1cc9","community_modular-meetup-toolkit.md":"9d9615a5","developers_prompt-scavenger.md":"344f4964","nodes_celestia-node.md":"c67af54b","developers_arbitrum-integration.md":"3383fe84","nodes_consensus-node.md":"a200c23b","nodes_mainnet.md":"80064b2d","developers_optimism.md":"cdea7c57","nodes_celestia-app.md":"1a57a3e1","nodes_celestia-app-multisig.md":"e6e77d19","developers_arbitrum-full-node.md":"5c121895","learn_how-celestia-works_data-availability-layer.md":"0cfb0e52","developers_rust-client-tutorial.md":"107ce036","nodes_celestia-node-metrics.md":"2a5b65d2","nodes_celestia-node-trusted-hash.md":"d4c8d8fc","index.md":"c4541c70","nodes_validator-node.md":"48b0877f","nodes_celestia-app-vesting.md":"f89a9306","learn_how-celestia-works_transaction-lifecycle.md":"ca3e89a7","nodes_celestia-node-troubleshooting.md":"df4f0579","developers_blobstream-offchain.md":"151b0bcb","nodes_arabica-devnet.md":"40301672","nodes_celestia-app-metrics.md":"475e4d25","developers_node-tutorial.md":"93ca0896","learn_paying-for-blobspace.md":"620633f6","developers_optimism-devnet.md":"8810346e","developers_deploy-on-bubs.md":"5777bbe3","learn_how-celestia-works_data-availability-faq.md":"a6c1dfca","learn_retrievability.md":"50d78947","developers_celestia-node-key.md":"46626500","developers_node-api.md":"ce423bd7","developers_arbitrum-smart-contract.md":"9848631a","developers_submit-data.md":"2f4ea658","developers_build-whatever.md":"4b218ab4","nodes_bridge-node.md":"59735aff","learn_staking-governance-supply.md":"8e057ee3","developers_bubs-testnet.md":"d6d65c34","nodes_full-storage-node.md":"5e7b39cd","developers_transaction-resubmission.md":"d55da8a7","developers_blobstream-x-deploy.md":"7f4b1f94","community_modular-meetup-guide.md":"d2586718","nodes_environment.md":"d129875e","nodes_celestia-app-commands.md":"2e95e351","nodes_docker-images.md":"dd8faa72","developers_blobstream-proof-queries.md":"4268c282"}
